openapi_client_generator/__init__.py
openapi_client_generator/api_generator.py
openapi_client_generator/api_generator_old.py
openapi_client_generator/base_api_generator.py
openapi_client_generator/cli.py
openapi_client_generator/generator.py
openapi_client_generator/model_generator.py
openapi_client_generator/openapi30_api_generator.py
openapi_client_generator/py.typed
openapi_client_generator/spec_loader.py
openapi_client_generator/swagger20_api_generator.py
openapi_client_generator/utils.py
openapi_client_python-0.1.2.dist-info/licenses/LICENSE
openapi_client_python-0.1.2.dist-info/METADATA
openapi_client_python-0.1.2.dist-info/WHEEL
openapi_client_python-0.1.2.dist-info/entry_points.txt
openapi_client_python-0.1.2.dist-info/top_level.txt
openapi_client_python-0.1.2.dist-info/RECORD
