Metadata-Version: 2.4
Name: openapi-client-python
Version: 0.1.2
Summary: A powerful tool that generates strongly-typed Python clients from OpenAPI 3.0 and Swagger 2.0 specifications
Home-page: https://github.com/autoocto/openapi-client-python
Author: autoocto
Author-email: AutoOcto <contact@autoocto.com>
Maintainer-email: AutoOcto <contact@autoocto.com>
License: MIT
Project-URL: Homepage, https://github.com/autoocto/openapi-client-python
Project-URL: Documentation, https://github.com/autoocto/openapi-client-python#readme
Project-URL: Repository, https://github.com/autoocto/openapi-client-python
Project-URL: Bug Tracker, https://github.com/autoocto/openapi-client-python/issues
Project-URL: Changelog, https://github.com/autoocto/openapi-client-python#changelog
Keywords: openapi,swagger,client,generator,api,rest,python,typing,code-generation
Classifier: Development Status :: 4 - Beta
Classifier: Intended Audience :: Developers
Classifier: License :: OSI Approved :: MIT License
Classifier: Operating System :: OS Independent
Classifier: Programming Language :: Python :: 3
Classifier: Programming Language :: Python :: 3.7
Classifier: Programming Language :: Python :: 3.8
Classifier: Programming Language :: Python :: 3.9
Classifier: Programming Language :: Python :: 3.10
Classifier: Programming Language :: Python :: 3.11
Classifier: Programming Language :: Python :: 3.12
Classifier: Topic :: Software Development :: Libraries :: Python Modules
Classifier: Topic :: Software Development :: Code Generators
Classifier: Topic :: Internet :: WWW/HTTP
Classifier: Topic :: Software Development :: Libraries
Classifier: Typing :: Typed
Requires-Python: >=3.7
License-File: LICENSE
Requires-Dist: requests>=2.25.0
Provides-Extra: dev
Requires-Dist: pytest>=6.0; extra == "dev"
Requires-Dist: pytest-cov>=2.0; extra == "dev"
Requires-Dist: black>=21.0; extra == "dev"
Requires-Dist: flake8>=3.8; extra == "dev"
Requires-Dist: mypy>=0.800; extra == "dev"
Provides-Extra: test
Requires-Dist: pytest>=6.0; extra == "test"
Requires-Dist: pytest-cov>=2.0; extra == "test"
Dynamic: author
Dynamic: home-page
Dynamic: license-file
Dynamic: requires-python
